SBself/__init__.py
SBself/config.py
SBself/core/__init__.py
SBself/core/core_cmds.py
SBself/core/core_commands.py
SBself/core/edit_and_reply.py
SBself/core/final_text.py
SBself/core/gp_id_manager.py
SBself/core/id_manager.py
SBself/core/logger.py
SBself/core/name_manager.py
SBself/core/off_manager.py
SBself/core/show_manager.py
SBself/core/startup_announcer.py
SBself/core/utils.py
SBself/filters/SBfilters.py
SBself/handlers/__init__.py
SBself/handlers/main.py
SBself/help/__init__.py
SBself/help/help.py
SBself/modules/__init__.py
SBself/modules/admin/__init__.py
SBself/modules/admin/admin_commands.py
SBself/modules/admin/admin_manager.py
SBself/modules/anti_login/__init__.py
SBself/modules/anti_login/commands.py
SBself/modules/anti_login/manager.py
SBself/modules/anti_login/utils.py
SBself/modules/backup/__init__.py
SBself/modules/backup/backup_commands.py
SBself/modules/backup/backup_manager.py
SBself/modules/chat/__init__.py
SBself/modules/chat/chat_cleaner.py
SBself/modules/chat/chat_cmds.py
SBself/modules/chat/chat_commands.py
SBself/modules/chat/chat_manager.py
SBself/modules/enemy/__init__.py
SBself/modules/enemy/enemy_commands.py
SBself/modules/enemy/enemy_handlers.py
SBself/modules/enemy/enemy_manager.py
SBself/modules/forward/__init__.py
SBself/modules/forward/forward_cmds.py
SBself/modules/forward/forward_commands.py
SBself/modules/forward/forward_manager.py
SBself/modules/forward/forward_queue_manager.py
SBself/modules/forward/forward_saveall_commands.py
SBself/modules/forward/multi_forward_cmds.py
SBself/modules/forward/multi_forward_manager.py
SBself/modules/get_code_login/__init__.py
SBself/modules/get_code_login/getcode_commands.py
SBself/modules/id/__init__.py
SBself/modules/id/id_commands.py
SBself/modules/member/__init__.py
SBself/modules/member/member_handlers.py
SBself/modules/mention/__init__.py
SBself/modules/mention/mention_commands.py
SBself/modules/mention/mention_manager.py
SBself/modules/profile/__init__.py
cliself-1.3.79.dist-info/licenses/LICENSE
cliself-1.3.79.dist-info/METADATA
cliself-1.3.79.dist-info/WHEEL
cliself-1.3.79.dist-info/top_level.txt
cliself-1.3.79.dist-info/RECORD
